quantummeta_license/__init__.py
quantummeta_license/cli/__init__.py
quantummeta_license/cli/main.py
quantummeta_license/core/__init__.py
quantummeta_license/core/encryption.py
quantummeta_license/core/hardware.py
quantummeta_license/core/license_manager.py
quantummeta_license/core/usage_tracker.py
quantummeta_license/core/validation.py
quantummeta_license/server/__init__.py
quantummeta_license/server/main.py
quantummeta_license/utils/__init__.py
quantummeta_license-1.1.1.dist-info/licenses/LICENSE
quantummeta_license-1.1.1.dist-info/licenses/license_server.py
quantummeta_license-1.1.1.dist-info/METADATA
quantummeta_license-1.1.1.dist-info/WHEEL
quantummeta_license-1.1.1.dist-info/entry_points.txt
quantummeta_license-1.1.1.dist-info/top_level.txt
quantummeta_license-1.1.1.dist-info/RECORD
