Metadata-Version: 2.4
Name: quantummeta-license
Version: 1.1.1
Summary: Universal, secure licensing system for QuantumMeta ecosystem packages
Home-page: https://github.com/krish567366/license-server
Author: Krishna Bajpai
Author-email: Krishna Bajpai <bajpaikrishna715@gmail.com>
License: MIT
Project-URL: Homepage, https://github.com/krish567366/license-server
Project-URL: Documentation, https://krish567366.github.io/license-server
Project-URL: Repository, https://github.com/krish567366/license-server
Project-URL: Issues, https://github.com/krish567366/license-server/issues
Keywords: license,licensing,security,quantum,ai,agi
Classifier: Development Status :: 5 - Production/Stable
Classifier: Intended Audience :: Developers
Classifier: License :: OSI Approved :: MIT License
Classifier: Operating System :: OS Independent
Classifier: Programming Language :: Python :: 3
Classifier: Programming Language :: Python :: 3.8
Classifier: Programming Language :: Python :: 3.9
Classifier: Programming Language :: Python :: 3.10
Classifier: Programming Language :: Python :: 3.11
Classifier: Programming Language :: Python :: 3.12
Classifier: Topic :: Software Development :: Libraries :: Python Modules
Classifier: Topic :: Security :: Cryptography
Classifier: Topic :: System :: Systems Administration :: Authentication/Directory
Requires-Python: >=3.8
License-File: LICENSE
License-File: license_server.py
Requires-Dist: cryptography>=41.0.0
Requires-Dist: typer[all]>=0.9.0
Requires-Dist: pydantic>=2.0.0
Requires-Dist: psutil>=5.9.0
Requires-Dist: rich>=13.0.0
Requires-Dist: platformdirs>=3.0.0
Requires-Dist: fastapi>=0.104.0
Requires-Dist: uvicorn[standard]>=0.24.0
Requires-Dist: python-multipart>=0.0.6
Requires-Dist: jinja2>=3.1.0
Provides-Extra: dev
Requires-Dist: pytest>=7.0.0; extra == "dev"
Requires-Dist: pytest-cov>=4.0.0; extra == "dev"
Requires-Dist: black>=23.0.0; extra == "dev"
Requires-Dist: flake8>=6.0.0; extra == "dev"
Requires-Dist: mypy>=1.0.0; extra == "dev"
Requires-Dist: pre-commit>=3.0.0; extra == "dev"
Provides-Extra: server
Requires-Dist: python-dotenv>=1.0.0; extra == "server"
Requires-Dist: aiofiles>=23.0.0; extra == "server"
Requires-Dist: slowapi>=0.1.9; extra == "server"
Requires-Dist: python-jose[cryptography]>=3.3.0; extra == "server"
Requires-Dist: aiosmtplib>=3.0.0; extra == "server"
Provides-Extra: docs
Requires-Dist: mkdocs>=1.5.0; extra == "docs"
Requires-Dist: mkdocs-material>=9.0.0; extra == "docs"
Requires-Dist: mkdocs-autorefs>=0.5.0; extra == "docs"
Requires-Dist: mkdocstrings[python]>=0.22.0; extra == "docs"
Dynamic: author
Dynamic: home-page
Dynamic: license-file
Dynamic: requires-python
